bmc/__init__.py
bmc/cluster.py
bmc/exceptions.py
bmc/session.py
bmc/turing_pi_types.py
bmc/models/__init__.py
bmc/models/about.py
bmc/models/info.py
bmc/models/interface_details.py
bmc/models/node.py
bmc/models/other.py
bmc/models/storage_details.py
bmc/models/usb_mode.py
Turing_Pi_BMC-1.0.1.dist-info/LICENSE
Turing_Pi_BMC-1.0.1.dist-info/METADATA
Turing_Pi_BMC-1.0.1.dist-info/WHEEL
Turing_Pi_BMC-1.0.1.dist-info/top_level.txt
Turing_Pi_BMC-1.0.1.dist-info/RECORD
