Metadata-Version: 2.1
Name: Turing-Pi-BMC
Version: 1.0.1
Summary: Package to manage a Turing Pi 2 cluster using the BMC API
Home-page: https://github.com/petermcd/turing-pi-bmc
Author: Peter McDonald
Author-email: git@petermcdonald.co.uk
Project-URL: Bug Tracker, https://github.com/petermcd/turing-pi-bmc/issues
Project-URL: Source, https://github.com/petermcd/turing-pi-bmc
Classifier: Programming Language :: Python :: 3.9
Classifier: Programming Language :: Python :: 3.10
Classifier: Programming Language :: Python :: 3.11
Classifier: Programming Language :: Python :: 3.12
Classifier: License :: OSI Approved :: MIT License
Classifier: Operating System :: OS Independent
Classifier: Intended Audience :: Developers
Requires-Python: >=3.9
License-File: LICENSE
Requires-Dist: requests
Requires-Dist: semver
Provides-Extra: build
Requires-Dist: wheel ; extra == 'build'
Requires-Dist: build ; extra == 'build'
Provides-Extra: test
Requires-Dist: pre-commit ; extra == 'test'
